README.md
setup.py
async_event/__init__.py
async_event/async_engine.py
async_event.egg-info/PKG-INFO
async_event.egg-info/SOURCES.txt
async_event.egg-info/dependency_links.txt
async_event.egg-info/top_level.txt