Metadata-Version: 1.0
Name: async-event
Version: 0.1
Summary: An easy use Event engine based on asyncio, just so so...
Home-page: UNKNOWN
Author: somewheve
Author-email: somewheve@gmail.com
License: UNKNOWN
Platform: UNKNOWN
